nomad_camels_driver_agilent_33220a/agilent_33220a.py
nomad_camels_driver_agilent_33220a/agilent_33220a_ophyd.py
nomad_camels_driver_agilent_33220a/virtual_lab_manual.py
nomad_camels_driver_agilent_33220a-0.1.2.dist-info/licenses/LICENSE.txt
nomad_camels_driver_agilent_33220a-0.1.2.dist-info/METADATA
nomad_camels_driver_agilent_33220a-0.1.2.dist-info/WHEEL
nomad_camels_driver_agilent_33220a-0.1.2.dist-info/top_level.txt
nomad_camels_driver_agilent_33220a-0.1.2.dist-info/RECORD
