Metadata-Version: 2.4
Name: nomad_camels_driver_agilent_33220a
Version: 0.1.2
Summary: Device driver for the Agilent 33220a function generator.
Author-email: FAIRmat - HU Berlin <nomad-camels@fau.de>
Project-URL: GitHub Page, https://github.com/FAU-LAP/NOMAD-CAMELS
Project-URL: Documentation, https://fau-lap.github.io/NOMAD-CAMELS/doc/instruments/instruments.html
Classifier: Programming Language :: Python :: 3
Classifier: License :: OSI Approved :: GNU Lesser General Public License v2 (LGPLv2)
Requires-Python: >=3.9.6
License-File: LICENSE.txt
Requires-Dist: pymeasure
Requires-Dist: nomad-camels
Dynamic: license-file
